deblend_sofia_detections/__init__.py
deblend_sofia_detections/main.py
deblend_sofia_detections/catalogue/__init__.py
deblend_sofia_detections/catalogue/download.py
deblend_sofia_detections/catalogue/search.py
deblend_sofia_detections/config/__init__.py
deblend_sofia_detections/config/config.py
deblend_sofia_detections/config/functions.py
deblend_sofia_detections/deblending/__init__.py
deblend_sofia_detections/deblending/deblending.py
deblend_sofia_detections/deblending/image_manipulation.py
deblend_sofia_detections/deblending/peak_handling.py
deblend_sofia_detections/deblending/sofia_functions.py
deblend_sofia_detections/support/__init__.py
deblend_sofia_detections/support/errors.py
deblend_sofia_detections/support/support_functions.py
deblend_sofia_detections/support/system_functions.py
deblend_sofia_detections/support/table_functions.py
deblend_sofia_detections/template/__init__.py
deblend_sofia_detections/template/sofia_template.par
deblend_sofia_detections-0.0.2.dist-info/METADATA
deblend_sofia_detections-0.0.2.dist-info/WHEEL
deblend_sofia_detections-0.0.2.dist-info/entry_points.txt
deblend_sofia_detections-0.0.2.dist-info/licenses/LICENSE
deblend_sofia_detections-0.0.2.dist-info/RECORD
