Metadata-Version: 2.4
Name: deblend_sofia_detections
Version: 0.0.2
Summary: Development Status :: 4 - Beta
Project-URL: Homepage, https://github.com/PeterKamphuis/deblend_sofia_detections
Author-email: "P. Kamphuis" <peterkamphuisastronomy@gmail.com>
License-Expression: GPL-3.0-or-later
License-File: LICENSE
Classifier: Development Status :: 4 - Beta
Classifier: Intended Audience :: Science/Research
Classifier: Operating System :: POSIX :: Linux
Classifier: Programming Language :: Python :: 3
Classifier: Topic :: Scientific/Engineering :: Astronomy
Requires-Python: >=3.11
Requires-Dist: astropy>=7.1.0
Requires-Dist: astroquery
Requires-Dist: future-fstrings
Requires-Dist: importlib-metadata
Requires-Dist: importlib-resources>=3.3.0
Requires-Dist: make-moments>=1.0.8
Requires-Dist: omegaconf
Requires-Dist: photutils
Requires-Dist: psutil
Requires-Dist: scikit-image
Requires-Dist: scipy
